igfash/__init__.py
igfash/compute.py
igfash/gm.py
igfash/io.py
igfash/kde.py
igfash/mc.py
igfash/rate.py
igfash/window.py
igfash/gsim/lasocki_2013.py
igfash-0.2.2.dist-info/METADATA
igfash-0.2.2.dist-info/WHEEL
igfash-0.2.2.dist-info/RECORD
