Metadata-Version: 2.4
Name: igfash
Version: 0.2.2
Summary: Instytut GeoFizyki Anthropogenic Seismic Hazard
Project-URL: Homepage, https://github.com/francistong/igfash
Project-URL: Issues, https://github.com/francistong/igfash/issues
Author-email: Francis Tong <author@example.com>
License-Expression: GPL-3.0-or-later
Classifier: Operating System :: OS Independent
Classifier: Programming Language :: Python :: 3
Requires-Python: >=3.9
